piedpy/__init__.py
piedpy/clibuffer.py
piedpy/clistyle.py
piedpy/clitoolbar.py
piedpy/compat.py
piedpy/completion_refresher.py
piedpy/config.py
piedpy/key_bindings.py
piedpy/lexer.py
piedpy/magic.py
piedpy/main.py
piedpy/piedpyrc
piedpy/sqlcompleter.py
piedpy/sqlexecute.py
piedpy/packages/__init__.py
piedpy/packages/completion_engine.py
piedpy/packages/filepaths.py
piedpy/packages/parseutils.py
piedpy/packages/prompt_utils.py
piedpy/packages/paramiko_stub/__init__.py
piedpy/packages/special/__init__.py
piedpy/packages/special/dbcommands.py
piedpy/packages/special/delimitercommand.py
piedpy/packages/special/favoritequeries.py
piedpy/packages/special/iocommands.py
piedpy/packages/special/main.py
piedpy/packages/special/utils.py
piedpy/packages/tabular_output/__init__.py
piedpy/packages/tabular_output/sql_format.py
test/__init__.py
test/conftest.py
test/test_clistyle.py
test/test_completion_engine.py
test/test_completion_refresher.py
test/test_config.py
test/test_dbspecial.py
test/test_main.py
test/test_naive_completion.py
test/test_parseutils.py
test/test_prompt_utils.py
test/test_smart_completion_public_schema_only.py
test/test_special_iocommands.py
test/test_sqlexecute.py
test/test_tabular_output.py
test/utils.py
test/features/__init__.py
test/features/db_utils.py
test/features/environment.py
test/features/fixture_utils.py
test/features/wrappager.py
test/features/steps/__init__.py
test/features/steps/auto_vertical.py
test/features/steps/basic_commands.py
test/features/steps/connection.py
test/features/steps/crud_database.py
test/features/steps/crud_table.py
test/features/steps/iocommands.py
test/features/steps/named_queries.py
test/features/steps/specials.py
test/features/steps/utils.py
test/features/steps/wrappers.py
piedpy-2022.1.dist-info/METADATA
piedpy-2022.1.dist-info/WHEEL
piedpy-2022.1.dist-info/entry_points.txt
piedpy-2022.1.dist-info/top_level.txt
piedpy-2022.1.dist-info/RECORD
