Metadata-Version: 2.1
Name: piedpy
Version: 2022.1
Summary: Powerful Command-line toolkit for MySQL Database.
Home-page: https://piedpy.rtfd.io
Author: Gerrishon Sirere
Author-email: scalabli@pm.me
Maintainer: Scalabli.
Maintainer-email: scalabli@pm.me
License: MIT
Project-URL: Donate, https://ko-fi.com/scalabli
Project-URL: Documentation, https://piedpy.rtfd.io
Project-URL: Changes, https://piedpy.readthedocs.io/en/latest/changes.html
Project-URL: Source Code, https://github.com/scalabli/piedpy
Project-URL: Issue Tracker, https://github.com/scalabli/piedpy/issues/
Project-URL: Twitter, https://twitter.com/scalabli
Project-URL: Chat, https://gitter.im/scalabli
Platform: UNKNOWN
Classifier: Development Status :: 5 - Production/Stable
Classifier: Intended Audience :: Developers
Classifier: Environment :: Console
Classifier: License :: OSI Approved :: MIT License
Classifier: Operating System :: OS Independent
Classifier: Programming Language :: Python :: 3.8
Classifier: Programming Language :: Python :: 3.9
Classifier: Programming Language :: Python :: 3.10
Classifier: Programming Language :: SQL
Classifier: Topic :: Database
Classifier: Topic :: Database :: Front-Ends
Classifier: Topic :: Software Development
Classifier: Topic :: Software Development :: Libraries :: Python Modules
Requires-Python: >=3.8
Requires-Dist: PyMySQL (>=0.9.2)
Requires-Dist: cli-helpers[styles] (>=2.0.1)
Requires-Dist: configobj (>=5.0.5)
Requires-Dist: cryptography (>=1.0.0)
Requires-Dist: pyaes (>=1.6.1)
Requires-Dist: quo (>=2022.3)
Requires-Dist: sqlparse (<0.5.0,>=0.3.0)
Provides-Extra: ssh
Requires-Dist: paramiko ; extra == 'ssh'
